README.md
django_faucet_pipeline/__init__.py
django_faucet_pipeline/apps.py
django_faucet_pipeline/templatetags/__init__.py
django_faucet_pipeline/templatetags/faucet_pipeline.py
django_faucet_pipeline/tests/__init__.py
django_faucet_pipeline/tests/bad_manifest.json
django_faucet_pipeline/tests/conftest.py
django_faucet_pipeline/tests/manifest.json
django_faucet_pipeline/tests/settings.py
django_faucet_pipeline/tests/test_render_template.py
django_faucet_pipeline/tests/testapp/__init__.py
django_faucet_pipeline/tests/testapp/apps.py
django_faucet_pipeline/tests/testapp/templates/template.txt
django_faucet_pipeline-1.0.0.dist-info/LICENSE
django_faucet_pipeline-1.0.0.dist-info/WHEEL
django_faucet_pipeline-1.0.0.dist-info/METADATA
django_faucet_pipeline-1.0.0.dist-info/RECORD
