Metadata-Version: 2.1
Name: django-faucet-pipeline
Version: 1.0.0
Summary: A Django integration for faucet-pipeline
Home-page: https://github.com/ngrewe/django-faucet-pipeline
License: MIT
Author: Niels Grewe
Author-email: niels.grewe@halbordnung.de
Requires-Python: >=3.7,<4.0
Classifier: Framework :: Django
Classifier: License :: OSI Approved :: MIT License
Classifier: Programming Language :: Python :: 3
Classifier: Programming Language :: Python :: 3.7
Classifier: Programming Language :: Python :: 3.8
Requires-Dist: Django (>=2.2)
Project-URL: Repository, https://github.com/ngrewe/django-faucet-pipeline
